ellipticTest/fourchains_elliptic.cp312-win_amd64.pyd
fourchains_elliptic-0.0.1.dist-info/METADATA
fourchains_elliptic-0.0.1.dist-info/WHEEL
fourchains_elliptic-0.0.1.dist-info/top_level.txt
fourchains_elliptic-0.0.1.dist-info/RECORD
